ubuntu_package_download/__init__.py
ubuntu_package_download/cli.py
ubuntu_package_download/lib.py
ubuntu_package_download-0.0.9.dist-info/AUTHORS.rst
ubuntu_package_download-0.0.9.dist-info/LICENSE
ubuntu_package_download-0.0.9.dist-info/METADATA
ubuntu_package_download-0.0.9.dist-info/WHEEL
ubuntu_package_download-0.0.9.dist-info/entry_points.txt
ubuntu_package_download-0.0.9.dist-info/RECORD
