Metadata-Version: 2.3
Name: ubuntu_package_download
Version: 0.0.9
Summary: Helpful utility to download Ubuntu debian packages
License: GPL-3.0-only
Author: Philip Roche
Author-email: phil.roche@canonical.com
Maintainer: Philip Roche
Maintainer-email: phil.roche@canonical.com
Requires-Python: >=3.10,<4.0
Classifier: License :: OSI Approved :: GNU General Public License v3 (GPLv3)
Classifier: Programming Language :: Python :: 3
Classifier: Programming Language :: Python :: 3.10
Classifier: Programming Language :: Python :: 3.11
Classifier: Programming Language :: Python :: 3.12
Classifier: Programming Language :: Python :: 3.13
Requires-Dist: launchpadlib (>=2.0.0,<3.0.0)
Requires-Dist: python-debian (>=0.1.49,<0.2.0)
Requires-Dist: rich (>=13.7.1,<14.0.0)
Requires-Dist: typer (>=0.16.0,<0.17.0)
Project-URL: Bugs, https://github.com/canonical/ubuntu-package-download/issues
Project-URL: Changelog, https://github.com/canonical/ubuntu-package-download/blob/main/HISTORY.rst
Project-URL: homepage, https://github.com/canonical/ubuntu-package-download/
Project-URL: repository, https://github.com/canonical/ubuntu-package-download
